{"type":"FeatureCollection","features":[{"type":"Feature","properties":{"title":"Veracruz Flooding Response 1: Álamo, Mexico","id":5400},"geometry":{"type":"Point","coordinates":[-97.6724380059734,20.9019724394661]}},{"type":"Feature","properties":{"title":"Typhoon Ompong: Cagayan and Batanes Structures","id":5236},"geometry":{"type":"Point","coordinates":[121.747240879307,18.8593470154527]}},{"type":"Feature","properties":{"title":"Guinea Flood Response - Gaoual Roads","id":5182},"geometry":{"type":"Point","coordinates":[-13.3572497333204,11.7251477385725]}},{"type":"Feature","properties":{"title":"Tanzania missing buildings Mwanga District","id":5427},"geometry":{"type":"Point","coordinates":[37.6385252591535,-3.69810262753919]}},{"type":"Feature","properties":{"title":"Missing Maps - Nigeria - Niger Flooding Djebba-Lokoya","id":5334},"geometry":{"type":"Point","coordinates":[6.0071305918705,8.66680686741859]}},{"type":"Feature","properties":{"title":"Joinkrama Flooded Area Mapping. Nigeria","id":5323},"geometry":{"type":"Point","coordinates":[6.49756838956685,5.07155836451435]}},{"type":"Feature","properties":{"title":"DRC/Bundibugyo District Border Mapping","id":5307},"geometry":{"type":"Point","coordinates":[29.9023571310443,0.650051053822993]}},{"type":"Feature","properties":{"title":"Typhoon Ompong: Isabela Structures 1","id":5234},"geometry":{"type":"Point","coordinates":[122.204399806909,16.9572292235093]}},{"type":"Feature","properties":{"title":"Ebola 2018, DRC/Ntoroko District Border Mapping","id":5207},"geometry":{"type":"Point","coordinates":[30.2710121990189,1.08357516305285]}},{"type":"Feature","properties":{"title":"Ebola 2018, DRC/Kanungu District Border Roads Mapping","id":5171},"geometry":{"type":"Point","coordinates":[29.638815766461,-0.765965544201528]}},{"type":"Feature","properties":{"title":"India Flood Response 2018 - South of Kochi, India - 01","id":5170},"geometry":{"type":"Point","coordinates":[76.501163491796,9.35388455315477]}},{"type":"Feature","properties":{"title":"Uganda Crowd-sourcing Non-Camp Refugee Data - Roads (GPX Tracks) Mapping Arua District","id":4701},"geometry":{"type":"Point","coordinates":[31.136833015961,2.95227770387037]}},{"type":"Feature","properties":{"title":"Mapping Flood Affected Communities in Bangladesh (Panchagarh, Rangpur)","id":3630},"geometry":{"type":"Point","coordinates":[88.5754590338312,26.2851291051997]}},{"type":"Feature","properties":{"title":"Mindanao Region, Misamis Oriental (northern)","id":5435},"geometry":{"type":"Point","coordinates":[124.994799793291,8.76680642717642]}},{"type":"Feature","properties":{"title":"Panabo, Davao del Norte, Philippines - MapPH","id":5434},"geometry":{"type":"Point","coordinates":[125.654373572769,7.31201677488237]}},{"type":"Feature","properties":{"title":"Kiryandongo Refugee Settlement, Kiryandongo District, Uganda","id":5433},"geometry":{"type":"Point","coordinates":[32.1863985683423,1.933473366647]}},{"type":"Feature","properties":{"title":"Aruba, Venezuela situation response - West","id":5424},"geometry":{"type":"Point","coordinates":[-70.013671224702,12.5111237517081]}},{"type":"Feature","properties":{"title":"Missing Maps: Petare, Caracas, Venezuela (4)","id":5417},"geometry":{"type":"Point","coordinates":[-66.7924293504179,10.4900877406547]}},{"type":"Feature","properties":{"title":"Aruba, Venezuela situation response - North","id":5403},"geometry":{"type":"Point","coordinates":[-70.0246738511366,12.5734030720378]}},{"type":"Feature","properties":{"title":"LISGIS City Mapping, Tappita City","id":5382},"geometry":{"type":"Point","coordinates":[-8.86073979113047,6.49184649716217]}},{"type":"Feature","properties":{"title":"Missing Maps: Chad, Moissala (part 1: Beboro)","id":5362},"geometry":{"type":"Point","coordinates":[17.6917335812731,8.57754029308444]}},{"type":"Feature","properties":{"title":"Missing Maps - Nigeria - Niger Flooding Kogi-Idah","id":5340},"geometry":{"type":"Point","coordinates":[6.72615528016713,7.42554483849386]}},{"type":"Feature","properties":{"title":"Ichnyansky District - Explosion Area","id":5337},"geometry":{"type":"Point","coordinates":[32.3322067150034,50.8024150844]}},{"type":"Feature","properties":{"title":"North-west","id":5327},"geometry":{"type":"Point","coordinates":[24.5495147016021,-13.5993734203055]}},{"type":"Feature","properties":{"title":"Missing Maps: Niger, Diffa","id":5324},"geometry":{"type":"Point","coordinates":[13.1572818725137,13.8333852839434]}},{"type":"Feature","properties":{"title":"Missing Maps: Embu county, Kenya (1)","id":5290},"geometry":{"type":"Point","coordinates":[37.582980506838,-0.797687500557701]}},{"type":"Feature","properties":{"title":"Missing Maps - Rombo Wildlife Conservancy, Kenya","id":5268},"geometry":{"type":"Point","coordinates":[37.7549046769582,-3.0287310278903]}},{"type":"Feature","properties":{"title":"2018 Ebola, South of Lubero, Nord-Kivu, DRC","id":5260},"geometry":{"type":"Point","coordinates":[29.2052350383231,-0.251116931803326]}},{"type":"Feature","properties":{"title":"Vingunguti","id":5218},"geometry":{"type":"Point","coordinates":[39.2283271509236,-6.845412414447]}},{"type":"Feature","properties":{"title":"Ndugumbi","id":5215},"geometry":{"type":"Point","coordinates":[39.2482813559023,-6.80125797617356]}},{"type":"Feature","properties":{"title":"Ebola 2018, DRC/Kasese District Border Mapping","id":5209},"geometry":{"type":"Point","coordinates":[29.7365617256048,0.06069365863441]}},{"type":"Feature","properties":{"title":"Makumbusho","id":5204},"geometry":{"type":"Point","coordinates":[39.2508110711774,-6.78966677791311]}},{"type":"Feature","properties":{"title":"Missing Maps: Residential areas in Moissala, Chad (3)","id":5179},"geometry":{"type":"Point","coordinates":[17.8983366481819,8.27351337683621]}},{"type":"Feature","properties":{"title":"Missing Maps: Residential areas in Moissala, Chad (2)","id":5178},"geometry":{"type":"Point","coordinates":[17.4658674340618,8.28219282860165]}},{"type":"Feature","properties":{"title":"DRC/Kanungu District Border Mapping - Buildings","id":5169},"geometry":{"type":"Point","coordinates":[29.6410887541837,-0.726509199805097]}},{"type":"Feature","properties":{"title":"ACAD_CSIAP_Killinochchi","id":5144},"geometry":{"type":"Point","coordinates":[80.2054912817065,9.37264837619135]}},{"type":"Feature","properties":{"title":"Missing Maps: South Central Myaungmya, Myanmar","id":5127},"geometry":{"type":"Point","coordinates":[95.2142568822246,16.6334984647143]}},{"type":"Feature","properties":{"title":"Missing Maps: South Central Myaungmya, Myanmar","id":5126},"geometry":{"type":"Point","coordinates":[95.0126648290332,16.4553726065755]}},{"type":"Feature","properties":{"title":"Missing Maps: Blue Nile State, Sudan (4)","id":5001},"geometry":{"type":"Point","coordinates":[33.929529076304,10.4946767570385]}},{"type":"Feature","properties":{"title":"Electrification project, North of Likasi, DRC","id":4952},"geometry":{"type":"Point","coordinates":[26.8083802973376,-10.6770837057262]}},{"type":"Feature","properties":{"title":"Tanzania Development Trust: Manyara FGM 2","id":4894},"geometry":{"type":"Point","coordinates":[36.5477142150534,-5.33552036818312]}},{"type":"Feature","properties":{"title":"Inhasorro, Mozambique - Vilankulo Bed Net Surveillance Program","id":4762},"geometry":{"type":"Point","coordinates":[35.2017156566584,-21.5476822465329]}},{"type":"Feature","properties":{"title":"Missing Maps: Canaan IV, Haiti","id":4446},"geometry":{"type":"Point","coordinates":[-72.2667456137484,18.6549119813216]}},{"type":"Feature","properties":{"title":"Healthcare access - Ifanadiana, Madagascar - 01","id":4408},"geometry":{"type":"Point","coordinates":[47.7421506394513,-20.9519745799664]}},{"type":"Feature","properties":{"title":"Missing Maps - Brickaville, Madagascar - DRR","id":4388},"geometry":{"type":"Point","coordinates":[48.8889944891731,-18.9671341764507]}},{"type":"Feature","properties":{"title":"Tanzania Development Trust: Simiyu South","id":4323},"geometry":{"type":"Point","coordinates":[34.3684346241635,-3.14466084541383]}},{"type":"Feature","properties":{"title":"Salesforce, Uganda Crowd-sourcing Non-Camp Refugee Data (Urban Mapping), Kibuye, Katwe, Makindye","id":4134},"geometry":{"type":"Point","coordinates":[32.5781360722246,0.290453912383011]}},{"type":"Feature","properties":{"title":"Missing Maps: Barguna Sadar Northeast, Bangladesh","id":4005},"geometry":{"type":"Point","coordinates":[90.1457719023543,22.1835531221325]}},{"type":"Feature","properties":{"title":"Tanzania Development Trust:  Mwanza East","id":3993},"geometry":{"type":"Point","coordinates":[33.1460082996701,-2.93920908459836]}},{"type":"Feature","properties":{"title":"Tanzania Development Trust: Manyoni district mapping project part 2","id":3389},"geometry":{"type":"Point","coordinates":[35.3323430025322,-4.33553146038057]}},{"type":"Feature","properties":{"title":"Flash flood in Solomon island","id":486},"geometry":{"type":"Point","coordinates":[159.975334731364,-9.44335033556199]}},{"type":"Feature","properties":{"title":"Olbia, Sardinia","id":369},"geometry":{"type":"Point","coordinates":[9.50948692215709,40.9334905060978]}},{"type":"Feature","properties":{"title":"Visayas, Philippines - Missing Roads Validation","id":5429},"geometry":{"type":"Point","coordinates":[123.412019883381,10.4668715968824]}},{"type":"Feature","properties":{"title":"Mapping for Rural First Responders","id":5420},"geometry":{"type":"Point","coordinates":[-105.098455916607,50.4396973250105]}},{"type":"Feature","properties":{"title":"Yatta","id":5319},"geometry":{"type":"Point","coordinates":[35.2021137892065,31.4011545541543]}},{"type":"Feature","properties":{"title":"Japan Earthquake, East Iburi, Hokkaido. 2018 : Atsuma area(Sep.6)","id":5220},"geometry":{"type":"Point","coordinates":[141.888836692357,42.6760340533639]}},{"type":"Feature","properties":{"title":"Tanzania Development Trust:  Manyara FGM 6","id":5136},"geometry":{"type":"Point","coordinates":[37.0715783941217,-6.08590867686194]}},{"type":"Feature","properties":{"title":"Khantia-Mansia, RU - Road Alignment","id":5109},"geometry":{"type":"Point","coordinates":[71.975901037221,61.2624729564418]}},{"type":"Feature","properties":{"title":"Arkhangelsk, RU - Road Alignment","id":5044},"geometry":{"type":"Point","coordinates":[42.0930614019958,62.114544765511]}},{"type":"Feature","properties":{"title":"Yaroslavl, RU - Road Alignment","id":5041},"geometry":{"type":"Point","coordinates":[39.1443497130268,57.5982859823097]}},{"type":"Feature","properties":{"title":"Smolensk, RU - Road Alignment","id":5039},"geometry":{"type":"Point","coordinates":[32.8547004619526,54.8764930805367]}},{"type":"Feature","properties":{"title":"St. Petersburg, RU - Road Alignment","id":5035},"geometry":{"type":"Point","coordinates":[30.23445185656,59.9410578806373]}},{"type":"Feature","properties":{"title":"Missing Maps: Central Java, Kota Semarang, Indonesia","id":4833},"geometry":{"type":"Point","coordinates":[110.384724939437,-7.02293729968189]}},{"type":"Feature","properties":{"title":"Missing Maps: Maluku Utara, Halmahera Utara, Indonesia","id":4832},"geometry":{"type":"Point","coordinates":[128.051421912438,1.85770681174287]}},{"type":"Feature","properties":{"title":"Missing Maps: Lake Chad - Nigeria, Yobe, Bade","id":4759},"geometry":{"type":"Point","coordinates":[10.8862293350879,12.7301361869864]}},{"type":"Feature","properties":{"title":"Missing Maps: Mawlamyine, Myanmar, South #4","id":4647},"geometry":{"type":"Point","coordinates":[97.6765077740323,15.9888485331612]}},{"type":"Feature","properties":{"title":"Healthcare access - Ifanadiana, Madagascar - 03","id":4410},"geometry":{"type":"Point","coordinates":[47.5922031420305,-21.3393654443129]}},{"type":"Feature","properties":{"title":"Healthcare access - Ifanadiana, Madagascar - 02","id":4409},"geometry":{"type":"Point","coordinates":[47.5415782411038,-20.9795934729345]}},{"type":"Feature","properties":{"title":"Afghanistan Roads Inventory - Kabul Province","id":4384},"geometry":{"type":"Point","coordinates":[69.3325935081014,34.5540663522964]}},{"type":"Feature","properties":{"title":"Afghanistan Roads Inventory - Ghor Province","id":4164},"geometry":{"type":"Point","coordinates":[64.928958701604,34.2238531344689]}},{"type":"Feature","properties":{"title":"Missing Maps: Bangladesh, Bagerhat Sadar","id":3893},"geometry":{"type":"Point","coordinates":[89.7632937630692,22.6775527819722]}},{"type":"Feature","properties":{"title":"Mapping Flood Affected Community in Nepal (Morang District, Biratnagar)","id":3473},"geometry":{"type":"Point","coordinates":[87.4701450775513,26.6174363834174]}},{"type":"Feature","properties":{"title":"Missing Maps - Malawi - Mwambo West (Roads)","id":3104},"geometry":{"type":"Point","coordinates":[35.4508401746668,-15.4526270023751]}},{"type":"Feature","properties":{"title":"Missing Maps: Lilongwe (central west), Lilongwe District, Central Region, Malawi","id":2154},"geometry":{"type":"Point","coordinates":[33.7552508718339,-13.9708636657718]}}]}