{"type":"FeatureCollection","features":[{"type":"Feature","properties":{"title":"Ebola2018, Beni, Nord-Kivu, DRC","id":4958},"geometry":{"type":"Point","coordinates":[29.46433009072933,0.4948085654413338]}},{"type":"Feature","properties":{"title":"Japan Flood 2018 July, Kure city, Hiroshima","id":4858},"geometry":{"type":"Point","coordinates":[132.65350479625798,34.28830288411048]}},{"type":"Feature","properties":{"title":"Sri Lanka Flood Response 2018 Project 4","id":4840},"geometry":{"type":"Point","coordinates":[80.00800340790637,7.776793538994095]}},{"type":"Feature","properties":{"title":"Open Cities Africa, Accra - Alogboshie II","id":4969},"geometry":{"type":"Point","coordinates":[-0.23110360611270842,5.634197922877294]}},{"type":"Feature","properties":{"title":"Sri Lanka Flood Response 2018 Project 5a","id":4898},"geometry":{"type":"Point","coordinates":[80.13172225161175,7.6380538705756535]}},{"type":"Feature","properties":{"title":"Missing Maps: Residential areas in Sokoto State, Nigeria (1)","id":4867},"geometry":{"type":"Point","coordinates":[6.4863856544465275,13.158865241025755]}},{"type":"Feature","properties":{"title":"Matete - Kisenso (DRR-Erosion)","id":4764},"geometry":{"type":"Point","coordinates":[15.339304126563874,-4.394328476368255]}},{"type":"Feature","properties":{"title":"Uganda Crowd-sourcing Non-Camp Refugee Data - Roads (GPX Tracks) Mapping Arua District","id":4701},"geometry":{"type":"Point","coordinates":[31.074578862085442,2.9228176868678046]}},{"type":"Feature","properties":{"title":"Missing Maps - Peru - Iquitos","id":4586},"geometry":{"type":"Point","coordinates":[-73.14220138876463,-3.6938852126741515]}},{"type":"Feature","properties":{"title":"Uganda Crowdsourcing Non-Camp Refugee Data (Urban Mapping) Kampala Nakawa Division Part 1","id":4371},"geometry":{"type":"Point","coordinates":[32.64702688918785,0.3114578744389416]}},{"type":"Feature","properties":{"title":"Lake Chad Region","id":4199},"geometry":{"type":"Point","coordinates":[14.24183517289722,13.48247367894081]}},{"type":"Feature","properties":{"title":"Mapping Flood Affected Community in Nepal (Morang District, Biratnagar)","id":3473},"geometry":{"type":"Point","coordinates":[87.41436987053658,26.652046649252412]}},{"type":"Feature","properties":{"title":"Ramani Huria and GreenWaste Colaboration","id":4976},"geometry":{"type":"Point","coordinates":[39.281588661377796,-6.822544597740107]}},{"type":"Feature","properties":{"title":"Clean Streets Kampala","id":4970},"geometry":{"type":"Point","coordinates":[32.59020637393066,0.3520817154793357]}},{"type":"Feature","properties":{"title":"Missing Maps: Bughendera County, Western Sub-Region, Uganda","id":4967},"geometry":{"type":"Point","coordinates":[30.067108268170816,0.6846905199330998]}},{"type":"Feature","properties":{"title":"Missing Maps: Bwamba County, Western Sub-Region, Uganda","id":4966},"geometry":{"type":"Point","coordinates":[30.00184564540891,0.7363033996814174]}},{"type":"Feature","properties":{"title":"Liberia LEGIT Project, Karnplay City","id":4935},"geometry":{"type":"Point","coordinates":[-8.503938414759247,7.273782902248913]}},{"type":"Feature","properties":{"title":"Bangladesh Refugee Crisis camp mapping - NW of megacamp 3 Update","id":4891},"geometry":{"type":"Point","coordinates":[92.14090672511095,21.210296467726188]}},{"type":"Feature","properties":{"title":"Open Cities Africa, Monrovia - Liberia","id":4866},"geometry":{"type":"Point","coordinates":[-10.792170767180165,6.328586129939864]}},{"type":"Feature","properties":{"title":"Tanzania Development Trust: Morogoro Community Mapping Project","id":4852},"geometry":{"type":"Point","coordinates":[37.68097780644893,-6.8100910041755895]}},{"type":"Feature","properties":{"title":"Open Schools Kenya-Kangemi Slum","id":4849},"geometry":{"type":"Point","coordinates":[36.74980515218077,-1.2711109069335746]}},{"type":"Feature","properties":{"title":"Cartographie du cercle de Koutiala","id":4789},"geometry":{"type":"Point","coordinates":[-5.589158340521111,12.011365817160838]}},{"type":"Feature","properties":{"title":"Vilankulo, Mozambique - Vilankulo Bed Net Surveillance Program","id":4746},"geometry":{"type":"Point","coordinates":[35.30021009270875,-21.982771993262052]}},{"type":"Feature","properties":{"title":"Missing Maps: Hoa Nhon, Da Nang, Viet Nam","id":4595},"geometry":{"type":"Point","coordinates":[108.11778095392042,16.016404351515657]}},{"type":"Feature","properties":{"title":"Istanbul, TR - Missing Roads","id":4520},"geometry":{"type":"Point","coordinates":[28.956042650483134,41.117615423675694]}},{"type":"Feature","properties":{"title":"Missing Maps: Mapping residential areas and buildings in Niger State, Nigeria (project 12)","id":4493},"geometry":{"type":"Point","coordinates":[6.564493180618725,9.979106982843954]}},{"type":"Feature","properties":{"title":"DRC Road network: Kivu (main roads based on CI/OR data)","id":4471},"geometry":{"type":"Point","coordinates":[27.499520779122957,-2.6038102755076293]}},{"type":"Feature","properties":{"title":"Missing Maps: Improving access to healthcare in Douentza, Mali (5)","id":4439},"geometry":{"type":"Point","coordinates":[-1.907740092360407,14.951357432306429]}},{"type":"Feature","properties":{"title":"Missing Maps: ONA-Ville, Canaan, Haiti","id":4421},"geometry":{"type":"Point","coordinates":[-72.24061081213189,18.672216654925556]}},{"type":"Feature","properties":{"title":"Tanzania Development Trust: Mwanza West Community Mapping Project","id":4358},"geometry":{"type":"Point","coordinates":[32.548552534014256,-2.6391112035937363]}},{"type":"Feature","properties":{"title":"Tanzania Development Trust: Simiyu South","id":4323},"geometry":{"type":"Point","coordinates":[34.2659914121032,-3.1020947645146095]}},{"type":"Feature","properties":{"title":"Tanzania Development Trust: Shinyanga East community mapping project","id":4166},"geometry":{"type":"Point","coordinates":[33.66405700164086,-3.5303866913753184]}},{"type":"Feature","properties":{"title":"Missing Maps: Barguna Sadar Southwest, Bangladesh","id":4007},"geometry":{"type":"Point","coordinates":[90.04298732474638,22.047596797275503]}},{"type":"Feature","properties":{"title":"Missing Maps: Tam Ky, Vietnam 2","id":3868},"geometry":{"type":"Point","coordinates":[108.5092704779448,15.609606878767911]}},{"type":"Feature","properties":{"title":"Missing Maps: Ha Tinh, Vietnam 2","id":3866},"geometry":{"type":"Point","coordinates":[105.89258069216868,18.356182891614953]}},{"type":"Feature","properties":{"title":"Missing Maps: Ha Tinh, Vietnam 1","id":3865},"geometry":{"type":"Point","coordinates":[105.91710515176096,18.325757268387065]}},{"type":"Feature","properties":{"title":"Peace Corps Senegal - Sanela","id":1266},"geometry":{"type":"Point","coordinates":[-11.73868238925935,12.749427760278232]}},{"type":"Feature","properties":{"title":"Netrokona Sadar Upazila, Bangladesh Health Workers Map","id":966},"geometry":{"type":"Point","coordinates":[90.74738019111429,24.894855039645464]}},{"type":"Feature","properties":{"title":"Missing Maps: Mawlamyine, Myanmar (roads clean-up)","id":4977},"geometry":{"type":"Point","coordinates":[97.63998492010708,16.44703435377184]}},{"type":"Feature","properties":{"title":"Missing Maps: Ndorwa County (NE part), Southwest Sub-Region, Uganda","id":4975},"geometry":{"type":"Point","coordinates":[30.048796394702602,-1.18192828370343]}},{"type":"Feature","properties":{"title":"Missing Maps: Ndorwa County (SW part), Southwest Sub-Region, Uganda","id":4974},"geometry":{"type":"Point","coordinates":[29.95089347385383,-1.3542261010252874]}},{"type":"Feature","properties":{"title":"Priority Areas, Northern Province, Zambia Mini Grids Project 10","id":4973},"geometry":{"type":"Point","coordinates":[32.98644706262053,-9.663965325485204]}},{"type":"Feature","properties":{"title":"Priority Areas, Northern Province, Zambia Mini Grids Project 08","id":4971},"geometry":{"type":"Point","coordinates":[31.906117131408344,-10.151719889685507]}},{"type":"Feature","properties":{"title":"Priority Areas, Muchinga, Zambia Mini Grids Project 11","id":4968},"geometry":{"type":"Point","coordinates":[32.9431977021841,-11.272851552957592]}},{"type":"Feature","properties":{"title":"Open Cities Africa, Accra - Day 1 - Maptime","id":4963},"geometry":{"type":"Point","coordinates":[-0.196507805585,5.681778300013334]}},{"type":"Feature","properties":{"title":"Priority Areas, Muchinga Province, Zambia Mini Grids Project 09","id":4954},"geometry":{"type":"Point","coordinates":[33.3766512603917,-10.25826517907981]}},{"type":"Feature","properties":{"title":"Settlement mapping exercise - Lake Sebu, SCO, PH","id":4934},"geometry":{"type":"Point","coordinates":[124.728200944321,6.347715540273485]}},{"type":"Feature","properties":{"title":"Priority Areas, North-Western Province, Zambia Mini Grids Project 06","id":4926},"geometry":{"type":"Point","coordinates":[24.186322722559076,-13.035832515232565]}},{"type":"Feature","properties":{"title":"Priority Areas, Northern Province, Zambia Mini Grids Project 04","id":4924},"geometry":{"type":"Point","coordinates":[31.748848823249283,-10.571409304008526]}},{"type":"Feature","properties":{"title":"Priority Areas, Northern Province, Zambia Mini Grids Project 03","id":4923},"geometry":{"type":"Point","coordinates":[30.592877456663988,-11.757584690536625]}},{"type":"Feature","properties":{"title":"PEPFAR: Côte d’Ivoire, Soubré","id":4913},"geometry":{"type":"Point","coordinates":[-6.5963474472268615,5.78897345880553]}},{"type":"Feature","properties":{"title":"Perú Friaje Relief: Roads and Rivers","id":4902},"geometry":{"type":"Point","coordinates":[-75.56619402072059,-12.783121891637647]}},{"type":"Feature","properties":{"title":"Tanzania Development Trust: Salesforce Manyara FGM 3","id":4896},"geometry":{"type":"Point","coordinates":[37.05802023052,-5.535989971496]}},{"type":"Feature","properties":{"title":"Tanzania Development Trust: Salesforce Manyara FGM 2","id":4894},"geometry":{"type":"Point","coordinates":[36.51992230814733,-5.409890486997332]}},{"type":"Feature","properties":{"title":"Tanzania Development Trust: Salesforce Manyara FGM 1","id":4892},"geometry":{"type":"Point","coordinates":[36.62758343996364,-5.541266902250907]}},{"type":"Feature","properties":{"title":"Lake Sebu village mapping exercise - P.M. Session","id":4875},"geometry":{"type":"Point","coordinates":[124.71676616156242,6.271326972480138]}},{"type":"Feature","properties":{"title":"Lake Sebu village mapping exercise - A.M. Session","id":4874},"geometry":{"type":"Point","coordinates":[124.72344320126112,6.289940875062825]}},{"type":"Feature","properties":{"title":"CRS-UP NOAH Building Footprints Mapping - Meycauayan, Bulacan","id":4793},"geometry":{"type":"Point","coordinates":[120.97247794046793,14.744349985853276]}},{"type":"Feature","properties":{"title":"Missing Maps: Mawlamyine, Myanmar, South #2","id":4644},"geometry":{"type":"Point","coordinates":[97.70429104328167,16.220942508576666]}},{"type":"Feature","properties":{"title":"Missing Maps: Cam Pho Ward, Da Nang, Viet Nam","id":4601},"geometry":{"type":"Point","coordinates":[108.32319234706529,15.880939585337895]}},{"type":"Feature","properties":{"title":"Concern Worldwide Disaster Risk Reduction (pilot) Gaga / Datoli, Central African Republic","id":4448},"geometry":{"type":"Point","coordinates":[16.97869646415265,5.48774680125175]}},{"type":"Feature","properties":{"title":"Healthcare access - Ifanadiana, Madagascar - 02","id":4409},"geometry":{"type":"Point","coordinates":[47.45186951076086,-20.912859812480814]}},{"type":"Feature","properties":{"title":"Missing Maps: Satkhira Sadar, Bangladesh","id":4041},"geometry":{"type":"Point","coordinates":[89.05253745620976,22.707803902573772]}},{"type":"Feature","properties":{"title":"Missing Maps: Bangladesh, Bagerhat Sadar","id":3893},"geometry":{"type":"Point","coordinates":[89.76075114269182,22.68450617961559]}},{"type":"Feature","properties":{"title":"Missing Maps: Iringa - OpenStreetMap Tanzania","id":3431},"geometry":{"type":"Point","coordinates":[35.70870872020667,-7.758966359486665]}},{"type":"Feature","properties":{"title":"Missing Maps - Malawi - Mwambo West (Roads)","id":3104},"geometry":{"type":"Point","coordinates":[35.44974083945572,-15.455271723316434]}},{"type":"Feature","properties":{"title":"Bamako (Mali)","id":1075},"geometry":{"type":"Point","coordinates":[-7.9726409912109375,12.596438965238207]}}]}